examples/__init__.py
examples/code_review_agent.py
examples/dependency_scan_agent.py
examples/log_analyzer.py
examples/optimization.py
examples/quickstart.py
examples/security_audit_agent.py
examples/web_agent.py
rec_praxis_rlm/__init__.py
rec_praxis_rlm/cli.py
rec_praxis_rlm/compression.py
rec_praxis_rlm/concepts.py
rec_praxis_rlm/config.py
rec_praxis_rlm/dspy_agent.py
rec_praxis_rlm/embeddings.py
rec_praxis_rlm/endless_mode.py
rec_praxis_rlm/errors.py
rec_praxis_rlm/exceptions.py
rec_praxis_rlm/experience_classifier.py
rec_praxis_rlm/fact_store.py
rec_praxis_rlm/formatters.py
rec_praxis_rlm/memory.py
rec_praxis_rlm/metrics.py
rec_praxis_rlm/privacy.py
rec_praxis_rlm/reporters.py
rec_praxis_rlm/rlm.py
rec_praxis_rlm/sandbox.py
rec_praxis_rlm/telemetry.py
rec_praxis_rlm/tools.py
rec_praxis_rlm/types.py
rec_praxis_rlm/web_viewer.py
rec_praxis_rlm/agents/__init__.py
rec_praxis_rlm/agents/code_review.py
rec_praxis_rlm/agents/dependency_scan.py
rec_praxis_rlm/agents/security_audit.py
rec_praxis_rlm/agents/test_generation.py
rec_praxis_rlm-0.9.2.dist-info/licenses/LICENSE
rec_praxis_rlm-0.9.2.dist-info/METADATA
rec_praxis_rlm-0.9.2.dist-info/WHEEL
rec_praxis_rlm-0.9.2.dist-info/entry_points.txt
rec_praxis_rlm-0.9.2.dist-info/top_level.txt
rec_praxis_rlm-0.9.2.dist-info/RECORD
