Metadata-Version: 2.4
Name: rec-praxis-rlm
Version: 0.9.2
Summary: Procedural memory + REPL context package with DSPy 3.0 integration for autonomous agents
Author-email: jmanhype <jmanhype@users.noreply.github.com>
License: MIT
Project-URL: Homepage, https://github.com/jmanhype/rec-praxis-rlm
Project-URL: Documentation, https://github.com/jmanhype/rec-praxis-rlm#readme
Project-URL: Repository, https://github.com/jmanhype/rec-praxis-rlm
Project-URL: Bug Tracker, https://github.com/jmanhype/rec-praxis-rlm/issues
Project-URL: PyPI, https://pypi.org/project/rec-praxis-rlm/
Keywords: dspy,procedural-memory,repl,autonomous-agents,mlflow
Classifier: Development Status :: 3 - Alpha
Classifier: Intended Audience :: Developers
Classifier: License :: OSI Approved :: MIT License
Classifier: Programming Language :: Python :: 3
Classifier: Programming Language :: Python :: 3.10
Classifier: Programming Language :: Python :: 3.11
Classifier: Programming Language :: Python :: 3.12
Classifier: Programming Language :: Python :: 3.13
Classifier: Topic :: Scientific/Engineering :: Artificial Intelligence
Requires-Python: >=3.10
License-File: LICENSE
Requires-Dist: dspy-ai>=3.0.4
Requires-Dist: pydantic>=2.0
Requires-Dist: sentence-transformers>=2.2
Requires-Dist: jsonlines>=3.0
Requires-Dist: mlflow>=3.0
Requires-Dist: tiktoken>=0.5.0
Provides-Extra: all
Requires-Dist: openai>=1.0; extra == "all"
Requires-Dist: aiofiles>=23.0; extra == "all"
Requires-Dist: faiss-cpu>=1.7; extra == "all"
Requires-Dist: requests>=2.28; extra == "all"
Provides-Extra: github
Requires-Dist: requests>=2.28; extra == "github"
Provides-Extra: test-generation
Requires-Dist: coverage>=7.0; extra == "test-generation"
Requires-Dist: pytest>=7.4; extra == "test-generation"
Requires-Dist: pytest-cov>=4.1; extra == "test-generation"
Provides-Extra: web
Requires-Dist: fastapi>=0.104; extra == "web"
Requires-Dist: uvicorn>=0.24; extra == "web"
Provides-Extra: dev
Requires-Dist: pytest>=7.4; extra == "dev"
Requires-Dist: pytest-cov>=4.1; extra == "dev"
Requires-Dist: pytest-asyncio>=0.21; extra == "dev"
Requires-Dist: coverage>=7.0; extra == "dev"
Requires-Dist: mypy>=1.5; extra == "dev"
Requires-Dist: ruff>=0.1; extra == "dev"
Requires-Dist: black>=23.0; extra == "dev"
Requires-Dist: bandit>=1.7; extra == "dev"
Requires-Dist: pdoc>=14.0; extra == "dev"
Dynamic: license-file
